pydantic_cache/__init__.py
pydantic_cache/coder.py
pydantic_cache/decorator.py
pydantic_cache/key_builder.py
pydantic_cache/sentinel.py
pydantic_cache/types.py
pydantic_cache/backends/__init__.py
pydantic_cache/backends/inmemory.py
pydantic_cache/backends/redis.py
pydantic_typed_cache-1.0.6.dist-info/licenses/LICENSE
pydantic_typed_cache-1.0.6.dist-info/METADATA
pydantic_typed_cache-1.0.6.dist-info/WHEEL
pydantic_typed_cache-1.0.6.dist-info/top_level.txt
pydantic_typed_cache-1.0.6.dist-info/RECORD
