Metadata-Version: 2.4
Name: pydantic-typed-cache
Version: 1.0.6
Summary: Async cache library for Pydantic models without FastAPI dependencies
Author-email: Wonderweeks Company <dev@mom-mom.net>
License: MIT
Project-URL: Homepage, https://github.com/mom-mom/pydantic-cache
Project-URL: Documentation, https://github.com/mom-mom/pydantic-cache#readme
Project-URL: Repository, https://github.com/mom-mom/pydantic-cache.git
Project-URL: Issues, https://github.com/mom-mom/pydantic-cache/issues
Project-URL: Inspiration, https://github.com/long2ice/fastapi-cache
Keywords: cache,pydantic,async,redis,asyncio,decorator
Classifier: Development Status :: 4 - Beta
Classifier: Intended Audience :: Developers
Classifier: License :: OSI Approved :: MIT License
Classifier: Programming Language :: Python :: 3
Classifier: Programming Language :: Python :: 3.13
Classifier: Topic :: Software Development :: Libraries :: Python Modules
Classifier: Framework :: Pydantic
Classifier: Framework :: AsyncIO
Requires-Python: <4.0,>=3.13
License-File: LICENSE
Requires-Dist: pydantic>=2.11.7
Requires-Dist: redis>=5.0.0
Requires-Dist: pendulum>=3.0.0
Provides-Extra: dev
Requires-Dist: pytest>=7.0.0; extra == "dev"
Requires-Dist: pytest-asyncio>=0.21.0; extra == "dev"
Requires-Dist: ruff>=0.12.8; extra == "dev"
Requires-Dist: pre-commit>=3.0.0; extra == "dev"
Provides-Extra: orjson
Requires-Dist: orjson>=3.9.0; extra == "orjson"
Dynamic: license-file
